hardcode_house_model/__init__.py
hardcode_house_model/data_accessor/__init__.py
hardcode_house_model/data_accessor/house_price_accessor.py
hardcode_house_model/data_accessor/spider_job_accessor.py
hardcode_house_model/house/__init__.py
hardcode_house_model/house/base.py
hardcode_house_model/house/common.py
hardcode_house_model/house/house_deal.py
hardcode_house_model/house/house_price.py
hardcode_house_model/house/spider_job.py
hardcode_house_model/statistics/__init__.py
hardcode_house_model/statistics/common.py
hardcode_house_model/statistics/housing_estate_price.py
hardcode_house_model/util/__init__.py
hardcode_house_model/util/bulk.py
hardcode_house_model/util/decorator.py
hardcode_house_model/util/mongo_mixin.py
hardcode_house_model-0.0.41.dist-info/LICENSE
hardcode_house_model-0.0.41.dist-info/METADATA
hardcode_house_model-0.0.41.dist-info/WHEEL
hardcode_house_model-0.0.41.dist-info/top_level.txt
hardcode_house_model-0.0.41.dist-info/RECORD
